docassemblecli3/__init__.py
docassemblecli3/__main__.py
docassemblecli3/docassemblecli3.py
docassemblecli3-0.4.0.dist-info/entry_points.txt
docassemblecli3-0.4.0.dist-info/licenses/LICENSE
docassemblecli3-0.4.0.dist-info/WHEEL
docassemblecli3-0.4.0.dist-info/METADATA
docassemblecli3-0.4.0.dist-info/RECORD
