Metadata-Version: 2.4
Name: docassemblecli3
Version: 0.4.0
Summary: Multi-platform CLI utility for working with docassemble packages and servers
Keywords: docassemble
Author-email: Jack Adamson <jackadamson@gmail.com>, Jonathan Pyle <jhpyle@gmail.com>
Requires-Python: >= 3.10
Classifier: License :: OSI Approved :: MIT License
Classifier: Programming Language :: Python
License-File: LICENSE
Requires-Dist: click
Requires-Dist: gitmatch
Requires-Dist: packaging
Requires-Dist: PyYAML
Requires-Dist: requests
Requires-Dist: watchdog
Project-URL: Bug Tracker, https://github.com/jpagh/docassemblecli3/issues
Project-URL: Homepage, https://github.com/jpagh/docassemblecli3
